[
  {
    "topic": "The One Animal a Great White Shark Runs From",
    "title": "The One Animal a Great White Shark Runs From",
    "publish_at": "2026-07-07T13:00:00Z",
    "ok": true,
    "video_url": "https://youtube.com/shorts/u8DHcc2ZmpY",
    "error": null,
    "elapsed_seconds": 271.2,
    "package_path": "state/trending_packages/20260707/01_orca-great-white-fear-2026.json",
    "video_path": "output/daily_20260707-114017_the_one_animal_a_great_white_shark_runs_.mp4",
    "qa": {
      "ok": true,
      "verdict": "ok",
      "reason": "short"
    },
    "channel": "default"
  },
  {
    "topic": "This 'Cute' Animal Is a Ruthless Killer",
    "title": "This 'Cute' Animal Is a Ruthless Killer",
    "publish_at": "2026-07-07T15:00:00Z",
    "ok": true,
    "video_url": "https://youtube.com/shorts/cBcUi6gIOLA",
    "error": null,
    "elapsed_seconds": 280.1,
    "package_path": "state/trending_packages/20260707/02_otter-cute-killer-2026.json",
    "video_path": "output/daily_20260707-114446_this__cute__animal_is_a_ruthless_killer.mp4",
    "qa": {
      "ok": true,
      "verdict": "ok",
      "reason": "short"
    },
    "channel": "default"
  },
  {
    "topic": "The Deadliest Big Animal in Africa Isn't the Lion",
    "title": "The Deadliest Big Animal in Africa Isn't the Lion",
    "publish_at": "2026-07-07T17:00:00Z",
    "ok": true,
    "video_url": "https://youtube.com/shorts/trZD_nPr2Bc",
    "error": null,
    "elapsed_seconds": 415.6,
    "package_path": "state/trending_packages/20260707/03_hippo-deadliest-africa-2026.json",
    "video_path": "output/daily_20260707-114930_the_deadliest_big_animal_in_africa_isn_t.mp4",
    "qa": {
      "ok": true,
      "verdict": "skip",
      "reason": "gemini unavailable"
    },
    "channel": "default"
  },
  {
    "topic": "The Bird That Can Kill You With One Kick",
    "title": "The Bird That Can Kill You With One Kick",
    "publish_at": "2026-07-07T19:00:00Z",
    "ok": true,
    "video_url": "https://youtube.com/shorts/Xqwqgn_slBU",
    "error": null,
    "elapsed_seconds": 350.9,
    "package_path": "state/trending_packages/20260707/04_cassowary-deadliest-bird-2026.json",
    "video_path": "output/daily_20260707-115602_the_bird_that_can_kill_you_with_one_kick.mp4",
    "qa": {
      "ok": true,
      "verdict": "ok",
      "reason": "short"
    },
    "channel": "default"
  },
  {
    "topic": "The Biggest Animal on Land Is Scared of Something Tiny",
    "title": "The Biggest Animal on Land Is Scared of Something Tiny",
    "publish_at": "2026-07-07T21:00:00Z",
    "ok": true,
    "video_url": "https://youtube.com/shorts/RVWDuSH2kAU",
    "error": null,
    "elapsed_seconds": 307.9,
    "package_path": "state/trending_packages/20260707/05_elephant-scared-of-bees-2026.json",
    "video_path": "output/daily_20260707-120217_the_biggest_animal_on_land_is_scared_of_.mp4",
    "qa": {
      "ok": true,
      "verdict": "ok",
      "reason": "short"
    },
    "channel": "default"
  },
  {
    "topic": "The Animal Too Fearless to Have Predators",
    "title": "The Animal Too Fearless to Have Predators",
    "publish_at": "2026-07-07T23:00:00Z",
    "ok": true,
    "video_url": "https://youtube.com/shorts/eNjf5maGyko",
    "error": null,
    "elapsed_seconds": 227.0,
    "package_path": "state/trending_packages/20260707/06_honey-badger-fearless-2026.json",
    "video_path": "output/daily_20260707-120719_the_animal_too_fearless_to_have_predator.mp4",
    "qa": {
      "ok": true,
      "verdict": "ok",
      "reason": "short"
    },
    "channel": "default"
  }
]
