{
  "_doc": "Pre-scored evergreen topic inventory. Built by build_topic_bank.py — edit TOPICS there and re-run, don't hand-edit this file. Weighted total = 3*hook+2*mystery+2*share+2*visual+2*cred+search+series (max 130). Greenlight >=85; cred<6 -> graveyard; visual<7 -> long-form only. Grow this toward 300-500 via the CONTENT_ENGINE sourcing funnel; every entry must be a REAL event (no padding).",
  "series": {
    "weird-wars": "Weird Wars",
    "disappearances": "Historical Disappearances",
    "impossible-artifacts": "Impossible Artifacts",
    "ancient-engineering": "Ancient Engineering",
    "made-up-humans": "Humans That Sound Made Up",
    "forgotten-disasters": "Forgotten Disasters",
    "medical-history": "Strange Medical History",
    "lost-expeditions": "Lost Expeditions"
  },
  "count": 121,
  "topics": [
    {
      "slug": "antikythera-mechanism",
      "title": "A 2,000-Year-Old Computer Found in a Shipwreck",
      "hook": "Ancient Greeks built a gear computer we couldn't match for 1,000 years.",
      "category": "impossible-artifacts",
      "series_id": "impossible-artifacts",
      "series_name": "Impossible Artifacts",
      "episode_number": 1,
      "fact_theory_note": "FACT: Antikythera mechanism, ~2nd c. BCE analog computer; function reconstructed.",
      "source_confidence": "high",
      "scores": {
        "hook": 10,
        "mystery": 9,
        "shareability": 10,
        "visual": 9,
        "credibility": 10,
        "search": 9,
        "series": 9,
        "total": 124
      },
      "shorts_eligible": true
    },
    {
      "slug": "voynich-manuscript",
      "title": "A Book No One Has Ever Been Able to Read",
      "hook": "600 years old, fully illustrated, in a language that doesn't exist.",
      "category": "impossible-artifacts",
      "series_id": "impossible-artifacts",
      "series_name": "Impossible Artifacts",
      "episode_number": 2,
      "fact_theory_note": "FACT: Voynich manuscript undeciphered; carbon-dated ~15th c.",
      "source_confidence": "high",
      "scores": {
        "hook": 10,
        "mystery": 10,
        "shareability": 10,
        "visual": 9,
        "credibility": 9,
        "search": 9,
        "series": 9,
        "total": 124
      },
      "shorts_eligible": true
    },
    {
      "slug": "roanoke",
      "title": "An Entire Colony Vanished, Leaving One Word",
      "hook": "120 settlers gone — only 'CROATOAN' carved in wood.",
      "category": "disappearances",
      "series_id": "disappearances",
      "series_name": "Historical Disappearances",
      "episode_number": 1,
      "fact_theory_note": "FACT: Roanoke colonists missing by 1590; 'CROATOAN' carving documented; fate is THEORY.",
      "source_confidence": "high",
      "scores": {
        "hook": 10,
        "mystery": 10,
        "shareability": 10,
        "visual": 8,
        "credibility": 9,
        "search": 9,
        "series": 9,
        "total": 122
      },
      "shorts_eligible": true
    },
    {
      "slug": "mary-celeste",
      "title": "A Ghost Ship Found With Everyone Gone",
      "hook": "Hot food, full cargo, not a soul aboard.",
      "category": "disappearances",
      "series_id": "disappearances",
      "series_name": "Historical Disappearances",
      "episode_number": 3,
      "fact_theory_note": "FACT: Mary Celeste found adrift 1872, crew never found; cause THEORY.",
      "source_confidence": "high",
      "scores": {
        "hook": 10,
        "mystery": 10,
        "shareability": 10,
        "visual": 8,
        "credibility": 9,
        "search": 9,
        "series": 9,
        "total": 122
      },
      "shorts_eligible": true
    },
    {
      "slug": "flannan-isles",
      "title": "Three Lighthouse Keepers Vanished Without a Trace",
      "hook": "The lamp was out, the door locked, the men gone.",
      "category": "disappearances",
      "series_id": "disappearances",
      "series_name": "Historical Disappearances",
      "episode_number": 2,
      "fact_theory_note": "FACT: 1900 Flannan Isles keepers vanished; cause is THEORY (rogue wave leading).",
      "source_confidence": "high",
      "scores": {
        "hook": 10,
        "mystery": 10,
        "shareability": 10,
        "visual": 8,
        "credibility": 9,
        "search": 8,
        "series": 9,
        "total": 121
      },
      "shorts_eligible": true
    },
    {
      "slug": "franklin-expedition",
      "title": "129 Men Sailed Into the Arctic and Were Never Seen Alive Again",
      "hook": "Two ships, frozen in, slowly vanished.",
      "category": "lost-expeditions",
      "series_id": "lost-expeditions",
      "series_name": "Lost Expeditions",
      "episode_number": 1,
      "fact_theory_note": "FACT: Franklin's 1845 expedition lost; ships found 2014/2016; details still THEORY.",
      "source_confidence": "high",
      "scores": {
        "hook": 10,
        "mystery": 10,
        "shareability": 10,
        "visual": 8,
        "credibility": 9,
        "search": 8,
        "series": 9,
        "total": 121
      },
      "shorts_eligible": true
    },
    {
      "slug": "tunguska-event",
      "title": "Something Flattened 800 Square Miles of Forest",
      "hook": "An explosion 1,000x Hiroshima — with no crater.",
      "category": "forgotten-disasters",
      "series_id": "forgotten-disasters",
      "series_name": "Forgotten Disasters",
      "episode_number": 4,
      "fact_theory_note": "FACT: 1908 Tunguska event; airburst THEORY (most accepted).",
      "source_confidence": "high",
      "scores": {
        "hook": 10,
        "mystery": 9,
        "shareability": 10,
        "visual": 8,
        "credibility": 9,
        "search": 8,
        "series": 8,
        "total": 118
      },
      "shorts_eligible": true
    },
    {
      "slug": "dyatlov-pass",
      "title": "Nine Hikers Fled Their Tent Into the Snow and Died",
      "hook": "They cut their way out half-dressed in -25C — no one knows why.",
      "category": "lost-expeditions",
      "series_id": "lost-expeditions",
      "series_name": "Lost Expeditions",
      "episode_number": 2,
      "fact_theory_note": "FACT: 1959 Dyatlov Pass deaths real; cause THEORY (avalanche model recent, still debated).",
      "source_confidence": "high",
      "scores": {
        "hook": 10,
        "mystery": 10,
        "shareability": 10,
        "visual": 7,
        "credibility": 8,
        "search": 9,
        "series": 9,
        "total": 118
      },
      "shorts_eligible": true
    },
    {
      "slug": "emu-war",
      "title": "Australia Lost a War to Birds in 1932",
      "hook": "Soldiers vs. 20,000 emus with machine guns — the birds won.",
      "category": "weird-wars",
      "series_id": "weird-wars",
      "series_name": "Weird Wars",
      "episode_number": 1,
      "fact_theory_note": "FACT: real 1932 military operation in WA; emus 'won'. Casualty/round figures well documented.",
      "source_confidence": "high",
      "scores": {
        "hook": 10,
        "mystery": 8,
        "shareability": 10,
        "visual": 8,
        "credibility": 9,
        "search": 9,
        "series": 8,
        "total": 117
      },
      "shorts_eligible": true
    },
    {
      "slug": "roman-dodecahedra",
      "title": "Romans Made These and We Still Don't Know Why",
      "hook": "Hundreds of bronze objects, zero written explanation.",
      "category": "impossible-artifacts",
      "series_id": "impossible-artifacts",
      "series_name": "Impossible Artifacts",
      "episode_number": 3,
      "fact_theory_note": "FACT: Roman dodecahedra exist; purpose unknown (THEORY).",
      "source_confidence": "high",
      "scores": {
        "hook": 9,
        "mystery": 10,
        "shareability": 9,
        "visual": 9,
        "credibility": 9,
        "search": 7,
        "series": 9,
        "total": 117
      },
      "shorts_eligible": true
    },
    {
      "slug": "greek-fire",
      "title": "A Weapon That Burned on Water and We Lost the Recipe",
      "hook": "The formula was so secret it died with the empire.",
      "category": "ancient-engineering",
      "series_id": "ancient-engineering",
      "series_name": "Ancient Engineering",
      "episode_number": 2,
      "fact_theory_note": "FACT: Greek fire real Byzantine weapon; exact recipe lost (THEORY on composition).",
      "source_confidence": "high",
      "scores": {
        "hook": 10,
        "mystery": 9,
        "shareability": 10,
        "visual": 8,
        "credibility": 8,
        "search": 8,
        "series": 8,
        "total": 116
      },
      "shorts_eligible": true
    },
    {
      "slug": "wojtek-bear",
      "title": "A Bear Was an Official Soldier in WWII",
      "hook": "He carried artillery shells and had a rank.",
      "category": "made-up-humans",
      "series_id": "made-up-humans",
      "series_name": "Humans That Sound Made Up",
      "episode_number": 2,
      "fact_theory_note": "FACT: Wojtek enlisted in the Polish II Corps; carried supplies.",
      "source_confidence": "high",
      "scores": {
        "hook": 10,
        "mystery": 8,
        "shareability": 10,
        "visual": 8,
        "credibility": 9,
        "search": 8,
        "series": 8,
        "total": 116
      },
      "shorts_eligible": true
    },
    {
      "slug": "dancing-plague-1518",
      "title": "In 1518, a Town Danced Itself to Death",
      "hook": "Hundreds danced for days — some until they died.",
      "category": "forgotten-disasters",
      "series_id": "forgotten-disasters",
      "series_name": "Forgotten Disasters",
      "episode_number": 1,
      "fact_theory_note": "FACT: Dancing Plague of 1518 in city records; cause THEORY (ergot vs mass hysteria).",
      "source_confidence": "high",
      "scores": {
        "hook": 10,
        "mystery": 9,
        "shareability": 9,
        "visual": 8,
        "credibility": 9,
        "search": 8,
        "series": 8,
        "total": 116
      },
      "shorts_eligible": true
    },
    {
      "slug": "phineas-gage",
      "title": "A Man Survived an Iron Rod Through His Brain",
      "hook": "A 3-foot spike shot through his skull — and he walked away.",
      "category": "medical-history",
      "series_id": "medical-history",
      "series_name": "Strange Medical History",
      "episode_number": 2,
      "fact_theory_note": "FACT: Phineas Gage, 1848; personality-change claims partly THEORY.",
      "source_confidence": "high",
      "scores": {
        "hook": 10,
        "mystery": 9,
        "shareability": 10,
        "visual": 7,
        "credibility": 9,
        "search": 8,
        "series": 8,
        "total": 116
      },
      "shorts_eligible": true
    },
    {
      "slug": "lake-nyos",
      "title": "A Lake Exploded and Suffocated a Whole Valley",
      "hook": "1,700 people died in their sleep from an invisible cloud.",
      "category": "forgotten-disasters",
      "series_id": "forgotten-disasters",
      "series_name": "Forgotten Disasters",
      "episode_number": 3,
      "fact_theory_note": "FACT: 1986 Lake Nyos limnic eruption; CO2 release.",
      "source_confidence": "high",
      "scores": {
        "hook": 10,
        "mystery": 9,
        "shareability": 10,
        "visual": 7,
        "credibility": 9,
        "search": 6,
        "series": 8,
        "total": 114
      },
      "shorts_eligible": true
    },
    {
      "slug": "radium-girls",
      "title": "Factory Workers Painted With Glowing Poison",
      "hook": "They licked radioactive brushes — and their bones rotted.",
      "category": "medical-history",
      "series_id": "medical-history",
      "series_name": "Strange Medical History",
      "episode_number": 1,
      "fact_theory_note": "FACT: Radium Girls, 1910s-20s; landmark labor/health case.",
      "source_confidence": "high",
      "scores": {
        "hook": 10,
        "mystery": 8,
        "shareability": 10,
        "visual": 7,
        "credibility": 9,
        "search": 8,
        "series": 8,
        "total": 114
      },
      "shorts_eligible": true
    },
    {
      "slug": "boston-molasses-flood",
      "title": "A Wave of Molasses Killed 21 People",
      "hook": "A 25-foot wall of syrup tore through Boston at 35 mph.",
      "category": "forgotten-disasters",
      "series_id": "forgotten-disasters",
      "series_name": "Forgotten Disasters",
      "episode_number": 2,
      "fact_theory_note": "FACT: 1919 Boston Molasses Flood; 21 dead, tank failure.",
      "source_confidence": "high",
      "scores": {
        "hook": 10,
        "mystery": 8,
        "shareability": 10,
        "visual": 7,
        "credibility": 9,
        "search": 7,
        "series": 8,
        "total": 113
      },
      "shorts_eligible": true
    },
    {
      "slug": "mallory-irvine",
      "title": "Did Two Climbers Reach Everest 29 Years Before Hillary?",
      "hook": "One body was found in 1999 — the other, and the camera, are still missing.",
      "category": "lost-expeditions",
      "series_id": "lost-expeditions",
      "series_name": "Lost Expeditions",
      "episode_number": 4,
      "fact_theory_note": "FACT: Mallory & Irvine vanished 1924; summit question unresolved (THEORY).",
      "source_confidence": "high",
      "scores": {
        "hook": 9,
        "mystery": 10,
        "shareability": 9,
        "visual": 8,
        "credibility": 8,
        "search": 8,
        "series": 8,
        "total": 113
      },
      "shorts_eligible": true
    },
    {
      "slug": "shackleton-endurance",
      "title": "A Ship Was Crushed by Ice and Everyone Still Survived",
      "hook": "Shackleton's open-boat journey is almost unbelievable.",
      "category": "lost-expeditions",
      "series_id": "lost-expeditions",
      "series_name": "Lost Expeditions",
      "episode_number": 11,
      "fact_theory_note": "FACT: Endurance 1914-17; all survived; wreck found 2022.",
      "source_confidence": "high",
      "scores": {
        "hook": 9,
        "mystery": 7,
        "shareability": 9,
        "visual": 9,
        "credibility": 10,
        "search": 8,
        "series": 8,
        "total": 113
      },
      "shorts_eligible": true
    },
    {
      "slug": "derinkuyu",
      "title": "A City for 20,000 People Hidden Underground",
      "hook": "An entire town carved beneath the earth.",
      "category": "ancient-engineering",
      "series_id": "ancient-engineering",
      "series_name": "Ancient Engineering",
      "episode_number": 3,
      "fact_theory_note": "FACT: Derinkuyu underground city, Cappadocia; capacity estimates vary.",
      "source_confidence": "high",
      "scores": {
        "hook": 9,
        "mystery": 8,
        "shareability": 9,
        "visual": 9,
        "credibility": 9,
        "search": 7,
        "series": 8,
        "total": 112
      },
      "shorts_eligible": true
    },
    {
      "slug": "lycurgus-cup",
      "title": "A Roman Cup That Changes Color Like Nanotech",
      "hook": "1,600 years ago, Romans used nanoparticles in glass.",
      "category": "impossible-artifacts",
      "series_id": "impossible-artifacts",
      "series_name": "Impossible Artifacts",
      "episode_number": 8,
      "fact_theory_note": "FACT: Lycurgus Cup uses colloidal gold/silver nanoparticles; dichroic effect real.",
      "source_confidence": "high",
      "scores": {
        "hook": 9,
        "mystery": 8,
        "shareability": 9,
        "visual": 9,
        "credibility": 9,
        "search": 6,
        "series": 8,
        "total": 111
      },
      "shorts_eligible": true
    },
    {
      "slug": "roman-concrete",
      "title": "Roman Concrete Heals Itself — Ours Crumbles",
      "hook": "2,000-year-old harbors are still standing.",
      "category": "ancient-engineering",
      "series_id": "ancient-engineering",
      "series_name": "Ancient Engineering",
      "episode_number": 1,
      "fact_theory_note": "FACT: Roman concrete's longevity and self-healing (lime clasts) studied/published.",
      "source_confidence": "high",
      "scores": {
        "hook": 9,
        "mystery": 8,
        "shareability": 9,
        "visual": 8,
        "credibility": 9,
        "search": 8,
        "series": 8,
        "total": 111
      },
      "shorts_eligible": true
    },
    {
      "slug": "rasputin",
      "title": "The Man Who Was Poisoned, Shot, and Still Wouldn't Die",
      "hook": "His murder reads like a horror movie.",
      "category": "made-up-humans",
      "series_id": "made-up-humans",
      "series_name": "Humans That Sound Made Up",
      "episode_number": 6,
      "fact_theory_note": "FACT/THEORY: Rasputin killed 1916; the 'unkillable' details are partly legend.",
      "source_confidence": "medium",
      "scores": {
        "hook": 10,
        "mystery": 8,
        "shareability": 10,
        "visual": 7,
        "credibility": 7,
        "search": 9,
        "series": 8,
        "total": 111
      },
      "shorts_eligible": true
    },
    {
      "slug": "andree-balloon",
      "title": "Three Men Tried to Reach the North Pole by Balloon",
      "hook": "Their fate was a mystery for 33 years — until their camera was found.",
      "category": "lost-expeditions",
      "series_id": "lost-expeditions",
      "series_name": "Lost Expeditions",
      "episode_number": 3,
      "fact_theory_note": "FACT: S.A. Andree's 1897 balloon expedition; remains/film found 1930.",
      "source_confidence": "high",
      "scores": {
        "hook": 9,
        "mystery": 9,
        "shareability": 9,
        "visual": 8,
        "credibility": 9,
        "search": 6,
        "series": 8,
        "total": 111
      },
      "shorts_eligible": true
    },
    {
      "slug": "flight-19",
      "title": "Five Bombers Vanished, Then So Did the Rescue Plane",
      "hook": "A whole squadron disappeared off Florida in 1945.",
      "category": "disappearances",
      "series_id": "disappearances",
      "series_name": "Historical Disappearances",
      "episode_number": 4,
      "fact_theory_note": "FACT: Flight 19 lost 1945; 'Bermuda Triangle' framing is THEORY — likely navigation error.",
      "source_confidence": "high",
      "scores": {
        "hook": 9,
        "mystery": 9,
        "shareability": 9,
        "visual": 7,
        "credibility": 8,
        "search": 9,
        "series": 8,
        "total": 110
      },
      "shorts_eligible": true
    },
    {
      "slug": "amelia-earhart",
      "title": "She Was Miles From Land When She Vanished",
      "hook": "The most famous pilot on Earth simply disappeared.",
      "category": "disappearances",
      "series_id": "disappearances",
      "series_name": "Historical Disappearances",
      "episode_number": 5,
      "fact_theory_note": "FACT: Earhart/Noonan lost 1937; resting place THEORY (Nikumaroro leading).",
      "source_confidence": "high",
      "scores": {
        "hook": 9,
        "mystery": 8,
        "shareability": 9,
        "visual": 7,
        "credibility": 9,
        "search": 9,
        "series": 8,
        "total": 110
      },
      "shorts_eligible": true
    },
    {
      "slug": "db-cooper",
      "title": "A Hijacker Parachuted Into the Night and Vanished",
      "hook": "He took the cash, jumped, and was never seen again.",
      "category": "disappearances",
      "series_id": "disappearances",
      "series_name": "Historical Disappearances",
      "episode_number": 6,
      "fact_theory_note": "FACT: 1971 D.B. Cooper hijacking; identity unsolved.",
      "source_confidence": "high",
      "scores": {
        "hook": 9,
        "mystery": 9,
        "shareability": 9,
        "visual": 7,
        "credibility": 8,
        "search": 9,
        "series": 8,
        "total": 110
      },
      "shorts_eligible": true
    },
    {
      "slug": "nan-madol",
      "title": "A Stone City Built on a Coral Reef in the Pacific",
      "hook": "Massive basalt 'logs' stacked in the ocean.",
      "category": "ancient-engineering",
      "series_id": "ancient-engineering",
      "series_name": "Ancient Engineering",
      "episode_number": 5,
      "fact_theory_note": "FACT: Nan Madol real; how stones were moved is THEORY.",
      "source_confidence": "high",
      "scores": {
        "hook": 9,
        "mystery": 9,
        "shareability": 9,
        "visual": 9,
        "credibility": 8,
        "search": 6,
        "series": 7,
        "total": 110
      },
      "shorts_eligible": true
    },
    {
      "slug": "tambora-1815",
      "title": "A Volcano Caused a Year Without Summer",
      "hook": "1816 had snow in June and crops failed worldwide.",
      "category": "forgotten-disasters",
      "series_id": "forgotten-disasters",
      "series_name": "Forgotten Disasters",
      "episode_number": 6,
      "fact_theory_note": "FACT: 1815 Mt Tambora eruption; 1816 'Year Without a Summer'.",
      "source_confidence": "high",
      "scores": {
        "hook": 9,
        "mystery": 8,
        "shareability": 9,
        "visual": 8,
        "credibility": 9,
        "search": 7,
        "series": 8,
        "total": 110
      },
      "shorts_eligible": true
    },
    {
      "slug": "eben-byers",
      "title": "A Man Drank Radioactive 'Health Water' Until His Jaw Fell Off",
      "hook": "The miracle tonic was slowly killing him.",
      "category": "medical-history",
      "series_id": "medical-history",
      "series_name": "Strange Medical History",
      "episode_number": 5,
      "fact_theory_note": "FACT: Eben Byers, Radithor, died 1932.",
      "source_confidence": "high",
      "scores": {
        "hook": 10,
        "mystery": 8,
        "shareability": 10,
        "visual": 6,
        "credibility": 9,
        "search": 6,
        "series": 8,
        "total": 110
      },
      "shorts_eligible": false
    },
    {
      "slug": "tarrare",
      "title": "A Man Who Could Eat Almost Anything and Never Get Full",
      "hook": "He ate live animals, corks, and a whole meal for 15.",
      "category": "made-up-humans",
      "series_id": "made-up-humans",
      "series_name": "Humans That Sound Made Up",
      "episode_number": 1,
      "fact_theory_note": "FACT/THEORY: Tarrare documented by military surgeons; some accounts likely exaggerated.",
      "source_confidence": "medium",
      "scores": {
        "hook": 10,
        "mystery": 9,
        "shareability": 10,
        "visual": 6,
        "credibility": 7,
        "search": 7,
        "series": 8,
        "total": 109
      },
      "shorts_eligible": false
    },
    {
      "slug": "jack-churchill",
      "title": "He Fought WWII With a Longbow and a Sword",
      "hook": "'Mad Jack' brought a claymore to a world war.",
      "category": "made-up-humans",
      "series_id": "made-up-humans",
      "series_name": "Humans That Sound Made Up",
      "episode_number": 4,
      "fact_theory_note": "FACT: Jack Churchill carried bow and sword; one longbow kill attested.",
      "source_confidence": "high",
      "scores": {
        "hook": 10,
        "mystery": 7,
        "shareability": 10,
        "visual": 7,
        "credibility": 8,
        "search": 7,
        "series": 8,
        "total": 109
      },
      "shorts_eligible": true
    },
    {
      "slug": "percy-fawcett",
      "title": "An Explorer Vanished Hunting a Lost City",
      "hook": "He walked into the Amazon for 'Z' and never returned.",
      "category": "disappearances",
      "series_id": "disappearances",
      "series_name": "Historical Disappearances",
      "episode_number": 7,
      "fact_theory_note": "FACT: Fawcett vanished 1925; fate THEORY.",
      "source_confidence": "high",
      "scores": {
        "hook": 9,
        "mystery": 9,
        "shareability": 9,
        "visual": 7,
        "credibility": 8,
        "search": 7,
        "series": 8,
        "total": 108
      },
      "shorts_eligible": true
    },
    {
      "slug": "london-beer-flood",
      "title": "A Tidal Wave of Beer Drowned People in London",
      "hook": "A burst vat sent 1 million litres into the streets.",
      "category": "forgotten-disasters",
      "series_id": "forgotten-disasters",
      "series_name": "Forgotten Disasters",
      "episode_number": 5,
      "fact_theory_note": "FACT: 1814 London Beer Flood; 8 dead.",
      "source_confidence": "high",
      "scores": {
        "hook": 10,
        "mystery": 8,
        "shareability": 10,
        "visual": 6,
        "credibility": 8,
        "search": 6,
        "series": 8,
        "total": 108
      },
      "shorts_eligible": false
    },
    {
      "slug": "halifax-explosion",
      "title": "The Biggest Man-Made Blast Before the Atom Bomb",
      "hook": "A ship collision leveled a city in 1917.",
      "category": "forgotten-disasters",
      "series_id": "forgotten-disasters",
      "series_name": "Forgotten Disasters",
      "episode_number": 7,
      "fact_theory_note": "FACT: 1917 Halifax Explosion; ~2,000 dead.",
      "source_confidence": "high",
      "scores": {
        "hook": 9,
        "mystery": 7,
        "shareability": 9,
        "visual": 8,
        "credibility": 9,
        "search": 7,
        "series": 8,
        "total": 108
      },
      "shorts_eligible": true
    },
    {
      "slug": "leonid-rogozov",
      "title": "A Doctor Removed His Own Appendix in Antarctica",
      "hook": "Stranded and dying, he operated on himself.",
      "category": "medical-history",
      "series_id": "medical-history",
      "series_name": "Strange Medical History",
      "episode_number": 3,
      "fact_theory_note": "FACT: Rogozov self-appendectomy, 1961.",
      "source_confidence": "high",
      "scores": {
        "hook": 10,
        "mystery": 7,
        "shareability": 10,
        "visual": 6,
        "credibility": 9,
        "search": 6,
        "series": 8,
        "total": 108
      },
      "shorts_eligible": false
    },
    {
      "slug": "louis-le-prince",
      "title": "The Father of Film Vanished Off a Moving Train",
      "hook": "He made the first movie, then disappeared days before fame.",
      "category": "disappearances",
      "series_id": "disappearances",
      "series_name": "Historical Disappearances",
      "episode_number": 8,
      "fact_theory_note": "FACT: Le Prince vanished 1890; cause unsolved.",
      "source_confidence": "high",
      "scores": {
        "hook": 9,
        "mystery": 9,
        "shareability": 9,
        "visual": 7,
        "credibility": 8,
        "search": 6,
        "series": 8,
        "total": 107
      },
      "shorts_eligible": true
    },
    {
      "slug": "carroll-deering",
      "title": "A Schooner Ran Aground With No Crew and a Pot of Food",
      "hook": "The ghost ship's entire crew was simply gone.",
      "category": "disappearances",
      "series_id": "disappearances",
      "series_name": "Historical Disappearances",
      "episode_number": 10,
      "fact_theory_note": "FACT: Carroll A. Deering found 1921; crew never found; cause THEORY.",
      "source_confidence": "high",
      "scores": {
        "hook": 9,
        "mystery": 9,
        "shareability": 9,
        "visual": 7,
        "credibility": 8,
        "search": 6,
        "series": 8,
        "total": 107
      },
      "shorts_eligible": true
    },
    {
      "slug": "baghdad-battery",
      "title": "A 2,000-Year-Old Jar That Looks Like a Battery",
      "hook": "Did ancient people have electricity?",
      "category": "impossible-artifacts",
      "series_id": "impossible-artifacts",
      "series_name": "Impossible Artifacts",
      "episode_number": 4,
      "fact_theory_note": "FACT: the artifacts exist; the 'battery' function is THEORY and widely doubted.",
      "source_confidence": "medium",
      "scores": {
        "hook": 9,
        "mystery": 9,
        "shareability": 9,
        "visual": 8,
        "credibility": 6,
        "search": 8,
        "series": 8,
        "total": 107
      },
      "shorts_eligible": true
    },
    {
      "slug": "ulfberht-swords",
      "title": "Viking Swords Made of Steel Too Advanced for Their Time",
      "hook": "Crucible steel that shouldn't have existed in Europe yet.",
      "category": "impossible-artifacts",
      "series_id": "impossible-artifacts",
      "series_name": "Impossible Artifacts",
      "episode_number": 10,
      "fact_theory_note": "FACT: +VLFBERH+T swords used high-purity crucible steel; sourcing debated (THEORY).",
      "source_confidence": "high",
      "scores": {
        "hook": 9,
        "mystery": 8,
        "shareability": 9,
        "visual": 8,
        "credibility": 8,
        "search": 6,
        "series": 8,
        "total": 107
      },
      "shorts_eligible": true
    },
    {
      "slug": "emperor-norton",
      "title": "A Broke Man Declared Himself Emperor — and a City Played Along",
      "hook": "San Francisco printed his money and obeyed his decrees.",
      "category": "made-up-humans",
      "series_id": "made-up-humans",
      "series_name": "Humans That Sound Made Up",
      "episode_number": 3,
      "fact_theory_note": "FACT: Joshua Norton, 'Emperor of the United States', 1859-1880.",
      "source_confidence": "high",
      "scores": {
        "hook": 9,
        "mystery": 8,
        "shareability": 9,
        "visual": 7,
        "credibility": 9,
        "search": 6,
        "series": 8,
        "total": 107
      },
      "shorts_eligible": true
    },
    {
      "slug": "trepanation",
      "title": "People Drilled Holes in Skulls 7,000 Years Ago — and Survived",
      "hook": "Healed bone shows many patients lived.",
      "category": "medical-history",
      "series_id": "medical-history",
      "series_name": "Strange Medical History",
      "episode_number": 6,
      "fact_theory_note": "FACT: trepanation is one of the oldest surgeries; survival shown by bone healing.",
      "source_confidence": "high",
      "scores": {
        "hook": 9,
        "mystery": 8,
        "shareability": 9,
        "visual": 7,
        "credibility": 9,
        "search": 6,
        "series": 8,
        "total": 107
      },
      "shorts_eligible": true
    },
    {
      "slug": "anglo-zanzibar-war",
      "title": "The War That Lasted 38 Minutes",
      "hook": "The shortest war in history was over before lunch.",
      "category": "weird-wars",
      "series_id": "weird-wars",
      "series_name": "Weird Wars",
      "episode_number": 2,
      "fact_theory_note": "FACT: 27 Aug 1896, ~38 min, Britain vs Zanzibar.",
      "source_confidence": "high",
      "scores": {
        "hook": 9,
        "mystery": 7,
        "shareability": 9,
        "visual": 7,
        "credibility": 9,
        "search": 8,
        "series": 7,
        "total": 106
      },
      "shorts_eligible": true
    },
    {
      "slug": "ching-shih",
      "title": "A Pirate Queen Who Commanded 80,000 Men",
      "hook": "She ran the largest pirate fleet in history — and retired rich.",
      "category": "made-up-humans",
      "series_id": "made-up-humans",
      "series_name": "Humans That Sound Made Up",
      "episode_number": 7,
      "fact_theory_note": "FACT: Zheng Yi Sao / Ching Shih led a vast Chinese pirate confederation.",
      "source_confidence": "high",
      "scores": {
        "hook": 9,
        "mystery": 8,
        "shareability": 9,
        "visual": 7,
        "credibility": 8,
        "search": 7,
        "series": 8,
        "total": 106
      },
      "shorts_eligible": true
    },
    {
      "slug": "tri-state-tornado",
      "title": "The Deadliest Tornado Stayed on the Ground for 3 Hours",
      "hook": "One twister crossed three states and killed 695.",
      "category": "forgotten-disasters",
      "series_id": "forgotten-disasters",
      "series_name": "Forgotten Disasters",
      "episode_number": 9,
      "fact_theory_note": "FACT: 1925 Tri-State Tornado; deadliest in US history.",
      "source_confidence": "high",
      "scores": {
        "hook": 9,
        "mystery": 7,
        "shareability": 9,
        "visual": 7,
        "credibility": 9,
        "search": 7,
        "series": 8,
        "total": 106
      },
      "shorts_eligible": true
    },
    {
      "slug": "semmelweis",
      "title": "The Doctor Mocked for Saying 'Wash Your Hands'",
      "hook": "He cut deaths by 90% — and was driven to an asylum.",
      "category": "medical-history",
      "series_id": "medical-history",
      "series_name": "Strange Medical History",
      "episode_number": 4,
      "fact_theory_note": "FACT: Ignaz Semmelweis, handwashing, 1840s; rejected in his time.",
      "source_confidence": "high",
      "scores": {
        "hook": 9,
        "mystery": 8,
        "shareability": 9,
        "visual": 6,
        "credibility": 9,
        "search": 7,
        "series": 8,
        "total": 106
      },
      "shorts_eligible": false
    },
    {
      "slug": "donner-party",
      "title": "A Wagon Train Trapped in the Snow Faced the Unthinkable",
      "hook": "Stranded for months, survivors did what they had to.",
      "category": "lost-expeditions",
      "series_id": "lost-expeditions",
      "series_name": "Lost Expeditions",
      "episode_number": 5,
      "fact_theory_note": "FACT: Donner Party, 1846-47; cannibalism attested by survivors.",
      "source_confidence": "high",
      "scores": {
        "hook": 9,
        "mystery": 8,
        "shareability": 9,
        "visual": 6,
        "credibility": 9,
        "search": 7,
        "series": 8,
        "total": 106
      },
      "shorts_eligible": false
    },
    {
      "slug": "war-of-bucket",
      "title": "Two Cities Went to War Over a Stolen Bucket",
      "hook": "Thousands died over a wooden pail in 1325.",
      "category": "weird-wars",
      "series_id": "weird-wars",
      "series_name": "Weird Wars",
      "episode_number": 3,
      "fact_theory_note": "FACT: 1325 Modena vs Bologna; the bucket is still displayed. Death toll figures vary.",
      "source_confidence": "medium",
      "scores": {
        "hook": 9,
        "mystery": 8,
        "shareability": 9,
        "visual": 7,
        "credibility": 8,
        "search": 7,
        "series": 7,
        "total": 105
      },
      "shorts_eligible": true
    },
    {
      "slug": "hugh-glass",
      "title": "Mauled by a Bear and Left for Dead, He Crawled 200 Miles",
      "hook": "Half-dead, he dragged himself across the wilderness for revenge.",
      "category": "made-up-humans",
      "series_id": "made-up-humans",
      "series_name": "Humans That Sound Made Up",
      "episode_number": 5,
      "fact_theory_note": "FACT/THEORY: Glass's 1823 ordeal real; distance/details embellished over time.",
      "source_confidence": "medium",
      "scores": {
        "hook": 9,
        "mystery": 8,
        "shareability": 9,
        "visual": 7,
        "credibility": 7,
        "search": 8,
        "series": 8,
        "total": 105
      },
      "shorts_eligible": true
    },
    {
      "slug": "juan-pujol-garbo",
      "title": "A Spy Who Tricked the Nazis With a Fake Army",
      "hook": "He invented agents who never existed and won medals from both sides.",
      "category": "made-up-humans",
      "series_id": "made-up-humans",
      "series_name": "Humans That Sound Made Up",
      "episode_number": 9,
      "fact_theory_note": "FACT: Juan Pujol Garcia ('Garbo'), double agent, D-Day deception.",
      "source_confidence": "high",
      "scores": {
        "hook": 9,
        "mystery": 8,
        "shareability": 9,
        "visual": 6,
        "credibility": 9,
        "search": 6,
        "series": 8,
        "total": 105
      },
      "shorts_eligible": false
    },
    {
      "slug": "peshtigo-fire",
      "title": "The Deadliest Fire in US History Was Forgotten",
      "hook": "It killed more than the Great Chicago Fire — the same night.",
      "category": "forgotten-disasters",
      "series_id": "forgotten-disasters",
      "series_name": "Forgotten Disasters",
      "episode_number": 10,
      "fact_theory_note": "FACT: 1871 Peshtigo Fire; overshadowed by Chicago.",
      "source_confidence": "high",
      "scores": {
        "hook": 9,
        "mystery": 8,
        "shareability": 9,
        "visual": 6,
        "credibility": 9,
        "search": 6,
        "series": 8,
        "total": 105
      },
      "shorts_eligible": false
    },
    {
      "slug": "sultana-explosion",
      "title": "America's Worst Maritime Disaster Was Buried in the News",
      "hook": "1,200 died — but it happened the week Lincoln was killed.",
      "category": "forgotten-disasters",
      "series_id": "forgotten-disasters",
      "series_name": "Forgotten Disasters",
      "episode_number": 12,
      "fact_theory_note": "FACT: 1865 Sultana explosion; overshadowed by Lincoln assassination.",
      "source_confidence": "high",
      "scores": {
        "hook": 9,
        "mystery": 8,
        "shareability": 9,
        "visual": 6,
        "credibility": 9,
        "search": 6,
        "series": 8,
        "total": 105
      },
      "shorts_eligible": false
    },
    {
      "slug": "walter-freeman-lobotomy",
      "title": "A Doctor Performed Brain Surgery With an Ice Pick",
      "hook": "He did thousands, sometimes in minutes, through the eye.",
      "category": "medical-history",
      "series_id": "medical-history",
      "series_name": "Strange Medical History",
      "episode_number": 7,
      "fact_theory_note": "FACT: Walter Freeman's transorbital lobotomy.",
      "source_confidence": "high",
      "scores": {
        "hook": 9,
        "mystery": 8,
        "shareability": 9,
        "visual": 6,
        "credibility": 9,
        "search": 6,
        "series": 8,
        "total": 105
      },
      "shorts_eligible": false
    },
    {
      "slug": "ninth-legion",
      "title": "A Roman Legion of 5,000 Men Disappeared From History",
      "hook": "Rome's 9th Legion marched north and stopped existing.",
      "category": "disappearances",
      "series_id": "disappearances",
      "series_name": "Historical Disappearances",
      "episode_number": 14,
      "fact_theory_note": "THEORY: Legio IX Hispana's fate debated; 'lost in Britain' is popular but contested by historians.",
      "source_confidence": "medium",
      "scores": {
        "hook": 9,
        "mystery": 9,
        "shareability": 9,
        "visual": 7,
        "credibility": 6,
        "search": 7,
        "series": 8,
        "total": 104
      },
      "shorts_eligible": true
    },
    {
      "slug": "nebra-sky-disc",
      "title": "The Oldest Map of the Sky Ever Found",
      "hook": "A Bronze Age disc showing real stars, 3,600 years old.",
      "category": "impossible-artifacts",
      "series_id": "impossible-artifacts",
      "series_name": "Impossible Artifacts",
      "episode_number": 6,
      "fact_theory_note": "FACT: Nebra sky disc, ~Bronze Age; dating debated by some but broadly accepted.",
      "source_confidence": "medium",
      "scores": {
        "hook": 8,
        "mystery": 8,
        "shareability": 8,
        "visual": 9,
        "credibility": 8,
        "search": 6,
        "series": 8,
        "total": 104
      },
      "shorts_eligible": true
    },
    {
      "slug": "old-tom-orca",
      "title": "Killer Whales That Teamed Up With Human Whalers",
      "hook": "Orcas herded whales to hunters — for a share of the kill.",
      "category": "made-up-humans",
      "series_id": "made-up-humans",
      "series_name": "Humans That Sound Made Up",
      "episode_number": 13,
      "fact_theory_note": "FACT: 'Law of the Tongue' at Eden, Australia; Old Tom's skeleton displayed.",
      "source_confidence": "high",
      "scores": {
        "hook": 9,
        "mystery": 8,
        "shareability": 9,
        "visual": 7,
        "credibility": 8,
        "search": 6,
        "series": 7,
        "total": 104
      },
      "shorts_eligible": true
    },
    {
      "slug": "safety-coffins",
      "title": "People Were So Afraid of Being Buried Alive They Built Escape Coffins",
      "hook": "Bells, air tubes, and 'I'm alive' flags for the dead.",
      "category": "medical-history",
      "series_id": "medical-history",
      "series_name": "Strange Medical History",
      "episode_number": 14,
      "fact_theory_note": "FACT: safety coffins patented in the 18th-19th c. amid premature-burial fears.",
      "source_confidence": "high",
      "scores": {
        "hook": 9,
        "mystery": 8,
        "shareability": 9,
        "visual": 7,
        "credibility": 8,
        "search": 6,
        "series": 7,
        "total": 104
      },
      "shorts_eligible": true
    },
    {
      "slug": "sodder-children",
      "title": "Five Kids Vanished in a Fire That Left No Bones",
      "hook": "The house burned — but the children were never found.",
      "category": "disappearances",
      "series_id": "disappearances",
      "series_name": "Historical Disappearances",
      "episode_number": 11,
      "fact_theory_note": "FACT: 1945 Sodder case; no remains recovered; fate unsolved/contested.",
      "source_confidence": "medium",
      "scores": {
        "hook": 9,
        "mystery": 9,
        "shareability": 9,
        "visual": 6,
        "credibility": 7,
        "search": 6,
        "series": 8,
        "total": 103
      },
      "shorts_eligible": false
    },
    {
      "slug": "costa-rica-spheres",
      "title": "Hundreds of Perfect Stone Balls in the Jungle",
      "hook": "Who carved them, and why nearly perfect spheres?",
      "category": "impossible-artifacts",
      "series_id": "impossible-artifacts",
      "series_name": "Impossible Artifacts",
      "episode_number": 11,
      "fact_theory_note": "FACT: Diquis spheres real; makers known (Diquis), exact purpose THEORY.",
      "source_confidence": "high",
      "scores": {
        "hook": 8,
        "mystery": 8,
        "shareability": 8,
        "visual": 9,
        "credibility": 8,
        "search": 6,
        "series": 7,
        "total": 103
      },
      "shorts_eligible": true
    },
    {
      "slug": "heron-aeolipile",
      "title": "Ancient Greeks Built a Steam Engine — for Fun",
      "hook": "A working steam device, 1,700 years before the Industrial Revolution.",
      "category": "ancient-engineering",
      "series_id": "ancient-engineering",
      "series_name": "Ancient Engineering",
      "episode_number": 6,
      "fact_theory_note": "FACT: Hero of Alexandria's aeolipile and devices described in his works.",
      "source_confidence": "high",
      "scores": {
        "hook": 9,
        "mystery": 7,
        "shareability": 9,
        "visual": 7,
        "credibility": 8,
        "search": 6,
        "series": 8,
        "total": 103
      },
      "shorts_eligible": true
    },
    {
      "slug": "saksaywaman",
      "title": "Stones So Tight You Can't Fit a Blade Between Them",
      "hook": "Giant boulders fitted without mortar.",
      "category": "ancient-engineering",
      "series_id": "ancient-engineering",
      "series_name": "Ancient Engineering",
      "episode_number": 7,
      "fact_theory_note": "FACT: Inca ashlar masonry at Saksaywaman; techniques partly understood.",
      "source_confidence": "high",
      "scores": {
        "hook": 8,
        "mystery": 8,
        "shareability": 8,
        "visual": 9,
        "credibility": 8,
        "search": 6,
        "series": 7,
        "total": 103
      },
      "shorts_eligible": true
    },
    {
      "slug": "stepwells-india",
      "title": "Upside-Down Temples Dug Hundreds of Feet Down",
      "hook": "Stairways descending into the earth for water.",
      "category": "ancient-engineering",
      "series_id": "ancient-engineering",
      "series_name": "Ancient Engineering",
      "episode_number": 10,
      "fact_theory_note": "FACT: Indian stepwells (e.g., Chand Baori) real and ancient.",
      "source_confidence": "high",
      "scores": {
        "hook": 8,
        "mystery": 7,
        "shareability": 8,
        "visual": 9,
        "credibility": 9,
        "search": 6,
        "series": 7,
        "total": 103
      },
      "shorts_eligible": true
    },
    {
      "slug": "banqiao-dam",
      "title": "A Dam Failure That May Have Killed 170,000",
      "hook": "Cascading dam collapses erased entire towns.",
      "category": "forgotten-disasters",
      "series_id": "forgotten-disasters",
      "series_name": "Forgotten Disasters",
      "episode_number": 11,
      "fact_theory_note": "FACT/THEORY: 1975 Banqiao failure; death toll estimates vary widely.",
      "source_confidence": "medium",
      "scores": {
        "hook": 9,
        "mystery": 8,
        "shareability": 9,
        "visual": 6,
        "credibility": 8,
        "search": 6,
        "series": 8,
        "total": 103
      },
      "shorts_eligible": false
    },
    {
      "slug": "clive-wearing",
      "title": "A Man Whose Memory Lasts Only Seconds",
      "hook": "Every moment, he believes he just woke up.",
      "category": "medical-history",
      "series_id": "medical-history",
      "series_name": "Strange Medical History",
      "episode_number": 9,
      "fact_theory_note": "FACT: Clive Wearing, amnesia after encephalitis.",
      "source_confidence": "high",
      "scores": {
        "hook": 9,
        "mystery": 8,
        "shareability": 9,
        "visual": 5,
        "credibility": 9,
        "search": 6,
        "series": 8,
        "total": 103
      },
      "shorts_eligible": false
    },
    {
      "slug": "corpse-medicine",
      "title": "Europeans Once Ate Mummies as Medicine",
      "hook": "Ground-up human remains were sold as a cure.",
      "category": "medical-history",
      "series_id": "medical-history",
      "series_name": "Strange Medical History",
      "episode_number": 11,
      "fact_theory_note": "FACT: 'mummia'/corpse medicine well documented in early modern Europe.",
      "source_confidence": "high",
      "scores": {
        "hook": 9,
        "mystery": 8,
        "shareability": 9,
        "visual": 6,
        "credibility": 8,
        "search": 6,
        "series": 8,
        "total": 103
      },
      "shorts_eligible": false
    },
    {
      "slug": "frederick-valentich",
      "title": "A Pilot Reported a Strange Object, Then Went Silent",
      "hook": "'It's not an aircraft' — then he and his plane vanished.",
      "category": "disappearances",
      "series_id": "disappearances",
      "series_name": "Historical Disappearances",
      "episode_number": 12,
      "fact_theory_note": "FACT: Valentich vanished 1978; UFO framing is THEORY, likely spatial disorientation.",
      "source_confidence": "medium",
      "scores": {
        "hook": 9,
        "mystery": 9,
        "shareability": 9,
        "visual": 5,
        "credibility": 7,
        "search": 7,
        "series": 8,
        "total": 102
      },
      "shorts_eligible": false
    },
    {
      "slug": "phaistos-disc",
      "title": "A Clay Disc Stamped With Symbols No One Can Decode",
      "hook": "The world's first 'typed' document is still unreadable.",
      "category": "impossible-artifacts",
      "series_id": "impossible-artifacts",
      "series_name": "Impossible Artifacts",
      "episode_number": 5,
      "fact_theory_note": "FACT: Phaistos Disc undeciphered; authenticity occasionally questioned (note).",
      "source_confidence": "medium",
      "scores": {
        "hook": 8,
        "mystery": 9,
        "shareability": 8,
        "visual": 8,
        "credibility": 7,
        "search": 6,
        "series": 8,
        "total": 102
      },
      "shorts_eligible": true
    },
    {
      "slug": "archimedes-claw",
      "title": "A Giant Claw That Lifted Roman Ships Out of the Water",
      "hook": "Archimedes built a war machine that flipped warships.",
      "category": "ancient-engineering",
      "series_id": "ancient-engineering",
      "series_name": "Ancient Engineering",
      "episode_number": 12,
      "fact_theory_note": "FACT/THEORY: Claw of Archimedes described by ancient sources; tested as plausible.",
      "source_confidence": "medium",
      "scores": {
        "hook": 9,
        "mystery": 8,
        "shareability": 9,
        "visual": 7,
        "credibility": 7,
        "search": 6,
        "series": 7,
        "total": 102
      },
      "shorts_eligible": true
    },
    {
      "slug": "burke-and-wills",
      "title": "They Crossed a Continent, Then Died Waiting at the Finish Line",
      "hook": "Rescue missed them by hours.",
      "category": "lost-expeditions",
      "series_id": "lost-expeditions",
      "series_name": "Lost Expeditions",
      "episode_number": 9,
      "fact_theory_note": "FACT: Burke and Wills, 1860-61 Australia.",
      "source_confidence": "high",
      "scores": {
        "hook": 8,
        "mystery": 8,
        "shareability": 8,
        "visual": 7,
        "credibility": 9,
        "search": 6,
        "series": 8,
        "total": 102
      },
      "shorts_eligible": true
    },
    {
      "slug": "henry-hudson-mutiny",
      "title": "An Explorer Was Set Adrift by His Own Crew and Vanished",
      "hook": "His men put him in a small boat and sailed home.",
      "category": "lost-expeditions",
      "series_id": "lost-expeditions",
      "series_name": "Lost Expeditions",
      "episode_number": 10,
      "fact_theory_note": "FACT: Hudson cast adrift 1611; fate unknown.",
      "source_confidence": "high",
      "scores": {
        "hook": 8,
        "mystery": 9,
        "shareability": 8,
        "visual": 7,
        "credibility": 8,
        "search": 6,
        "series": 8,
        "total": 102
      },
      "shorts_eligible": true
    },
    {
      "slug": "christmas-truce",
      "title": "Enemies Played Soccer Together in No Man's Land",
      "hook": "On Christmas 1914, the shooting just stopped.",
      "category": "weird-wars",
      "series_id": "weird-wars",
      "series_name": "Weird Wars",
      "episode_number": 7,
      "fact_theory_note": "FACT: 1914 Christmas Truce; football matches attested in some sectors.",
      "source_confidence": "high",
      "scores": {
        "hook": 8,
        "mystery": 6,
        "shareability": 8,
        "visual": 8,
        "credibility": 9,
        "search": 8,
        "series": 7,
        "total": 101
      },
      "shorts_eligible": true
    },
    {
      "slug": "iron-pillar-delhi",
      "title": "A 1,600-Year-Old Iron Pillar That Won't Rust",
      "hook": "Open-air iron that refuses to corrode.",
      "category": "impossible-artifacts",
      "series_id": "impossible-artifacts",
      "series_name": "Impossible Artifacts",
      "episode_number": 9,
      "fact_theory_note": "FACT: Iron Pillar of Delhi; corrosion resistance explained by passive film.",
      "source_confidence": "high",
      "scores": {
        "hook": 8,
        "mystery": 7,
        "shareability": 8,
        "visual": 8,
        "credibility": 9,
        "search": 6,
        "series": 7,
        "total": 101
      },
      "shorts_eligible": true
    },
    {
      "slug": "baiae-underwater",
      "title": "A Roman Resort Town Sank Beneath the Sea",
      "hook": "Marble villas now sit on the seafloor.",
      "category": "ancient-engineering",
      "series_id": "ancient-engineering",
      "series_name": "Ancient Engineering",
      "episode_number": 9,
      "fact_theory_note": "FACT: Baiae partly submerged by volcanic bradyseism; underwater park exists.",
      "source_confidence": "high",
      "scores": {
        "hook": 8,
        "mystery": 7,
        "shareability": 8,
        "visual": 9,
        "credibility": 8,
        "search": 6,
        "series": 7,
        "total": 101
      },
      "shorts_eligible": true
    },
    {
      "slug": "puma-punku",
      "title": "Stone Blocks Cut Like They Were Machined",
      "hook": "Precise H-blocks that puzzle engineers.",
      "category": "ancient-engineering",
      "series_id": "ancient-engineering",
      "series_name": "Ancient Engineering",
      "episode_number": 13,
      "fact_theory_note": "FACT: Puma Punku real Tiwanaku site; 'machined' framing exaggerated — note carefully.",
      "source_confidence": "medium",
      "scores": {
        "hook": 8,
        "mystery": 8,
        "shareability": 8,
        "visual": 9,
        "credibility": 7,
        "search": 6,
        "series": 7,
        "total": 101
      },
      "shorts_eligible": true
    },
    {
      "slug": "great-smog-1952",
      "title": "A Fog So Toxic It Killed Thousands in Days",
      "hook": "London's air turned deadly and nobody could see.",
      "category": "forgotten-disasters",
      "series_id": "forgotten-disasters",
      "series_name": "Forgotten Disasters",
      "episode_number": 8,
      "fact_theory_note": "FACT: 1952 Great Smog of London; thousands of excess deaths.",
      "source_confidence": "high",
      "scores": {
        "hook": 8,
        "mystery": 7,
        "shareability": 8,
        "visual": 7,
        "credibility": 9,
        "search": 7,
        "series": 8,
        "total": 101
      },
      "shorts_eligible": true
    },
    {
      "slug": "tobacco-enema",
      "title": "Doctors Once Blew Smoke Up People's Backsides to Save Them",
      "hook": "It's where the phrase comes from — literally.",
      "category": "medical-history",
      "series_id": "medical-history",
      "series_name": "Strange Medical History",
      "episode_number": 10,
      "fact_theory_note": "FACT: tobacco smoke enemas used for resuscitation, 18th c.",
      "source_confidence": "high",
      "scores": {
        "hook": 9,
        "mystery": 7,
        "shareability": 9,
        "visual": 6,
        "credibility": 8,
        "search": 6,
        "series": 8,
        "total": 101
      },
      "shorts_eligible": false
    },
    {
      "slug": "washington-bloodletting",
      "title": "Doctors May Have Bled a President to Death",
      "hook": "They drained ~40% of his blood trying to cure a sore throat.",
      "category": "medical-history",
      "series_id": "medical-history",
      "series_name": "Strange Medical History",
      "episode_number": 12,
      "fact_theory_note": "FACT/THEORY: Washington's 1799 treatment; bloodletting's role in death is debated.",
      "source_confidence": "medium",
      "scores": {
        "hook": 9,
        "mystery": 8,
        "shareability": 9,
        "visual": 5,
        "credibility": 8,
        "search": 7,
        "series": 7,
        "total": 101
      },
      "shorts_eligible": false
    },
    {
      "slug": "the-karluk",
      "title": "A Ship Crushed by Ice Left Its Crew on the Frozen Sea",
      "hook": "They walked across the ice as their ship sank.",
      "category": "lost-expeditions",
      "series_id": "lost-expeditions",
      "series_name": "Lost Expeditions",
      "episode_number": 6,
      "fact_theory_note": "FACT: Karluk disaster, 1913-16; survival story documented.",
      "source_confidence": "high",
      "scores": {
        "hook": 8,
        "mystery": 8,
        "shareability": 8,
        "visual": 7,
        "credibility": 9,
        "search": 5,
        "series": 8,
        "total": 101
      },
      "shorts_eligible": true
    },
    {
      "slug": "amundsen-disappearance",
      "title": "The Man Who Conquered the Poles Vanished on a Rescue",
      "hook": "He flew off to save a rival and was never found.",
      "category": "lost-expeditions",
      "series_id": "lost-expeditions",
      "series_name": "Lost Expeditions",
      "episode_number": 14,
      "fact_theory_note": "FACT: Amundsen disappeared 1928 during an Arctic rescue flight.",
      "source_confidence": "high",
      "scores": {
        "hook": 8,
        "mystery": 8,
        "shareability": 8,
        "visual": 6,
        "credibility": 9,
        "search": 7,
        "series": 8,
        "total": 101
      },
      "shorts_eligible": false
    },
    {
      "slug": "pig-war",
      "title": "A Dead Pig Almost Started a US-UK War",
      "hook": "One shot pig nearly triggered an international war in 1859.",
      "category": "weird-wars",
      "series_id": "weird-wars",
      "series_name": "Weird Wars",
      "episode_number": 4,
      "fact_theory_note": "FACT: 1859 San Juan Islands standoff; only casualty was a pig.",
      "source_confidence": "high",
      "scores": {
        "hook": 8,
        "mystery": 7,
        "shareability": 8,
        "visual": 7,
        "credibility": 9,
        "search": 7,
        "series": 7,
        "total": 100
      },
      "shorts_eligible": true
    },
    {
      "slug": "kettle-war",
      "title": "A War Ended After One Cannonball Hit a Soup Pot",
      "hook": "The only shot of the war struck a kettle.",
      "category": "weird-wars",
      "series_id": "weird-wars",
      "series_name": "Weird Wars",
      "episode_number": 6,
      "fact_theory_note": "FACT: 1784 Kettle War, Dutch vs Austrian Netherlands; near-bloodless.",
      "source_confidence": "medium",
      "scores": {
        "hook": 9,
        "mystery": 7,
        "shareability": 9,
        "visual": 6,
        "credibility": 8,
        "search": 6,
        "series": 7,
        "total": 100
      },
      "shorts_eligible": false
    },
    {
      "slug": "shroud-of-turin",
      "title": "The Cloth That Science Still Argues About",
      "hook": "A faint image no one can fully explain.",
      "category": "impossible-artifacts",
      "series_id": "impossible-artifacts",
      "series_name": "Impossible Artifacts",
      "episode_number": 14,
      "fact_theory_note": "CONTESTED: 1988 C-14 dated it medieval; debates continue. Frame as disputed, not proof.",
      "source_confidence": "medium",
      "scores": {
        "hook": 8,
        "mystery": 9,
        "shareability": 8,
        "visual": 7,
        "credibility": 6,
        "search": 9,
        "series": 7,
        "total": 100
      },
      "shorts_eligible": true
    },
    {
      "slug": "incitatus",
      "title": "A Roman Emperor Tried to Make His Horse a Senator",
      "hook": "Caligula gave his horse a house and servants.",
      "category": "made-up-humans",
      "series_id": "made-up-humans",
      "series_name": "Humans That Sound Made Up",
      "episode_number": 8,
      "fact_theory_note": "THEORY: Incitatus 'consul' story from hostile sources; likely satire/exaggeration — frame as claim.",
      "source_confidence": "medium",
      "scores": {
        "hook": 9,
        "mystery": 8,
        "shareability": 9,
        "visual": 6,
        "credibility": 6,
        "search": 8,
        "series": 7,
        "total": 100
      },
      "shorts_eligible": false
    },
    {
      "slug": "saint-guinefort",
      "title": "A Dog Was Worshipped as a Saint",
      "hook": "Medieval villagers prayed to a greyhound.",
      "category": "made-up-humans",
      "series_id": "made-up-humans",
      "series_name": "Humans That Sound Made Up",
      "episode_number": 14,
      "fact_theory_note": "FACT: cult of Saint Guinefort recorded by Inquisitor Stephen of Bourbon.",
      "source_confidence": "medium",
      "scores": {
        "hook": 9,
        "mystery": 8,
        "shareability": 9,
        "visual": 6,
        "credibility": 7,
        "search": 6,
        "series": 7,
        "total": 100
      },
      "shorts_eligible": false
    },
    {
      "slug": "john-snow-cholera",
      "title": "One Doctor Stopped an Epidemic by Removing a Pump Handle",
      "hook": "He mapped the deaths and traced them to a single well.",
      "category": "medical-history",
      "series_id": "medical-history",
      "series_name": "Strange Medical History",
      "episode_number": 13,
      "fact_theory_note": "FACT: John Snow, Broad Street pump, 1854; birth of epidemiology.",
      "source_confidence": "high",
      "scores": {
        "hook": 8,
        "mystery": 7,
        "shareability": 8,
        "visual": 7,
        "credibility": 9,
        "search": 7,
        "series": 7,
        "total": 100
      },
      "shorts_eligible": true
    },
    {
      "slug": "war-of-jenkins-ear",
      "title": "A War Named After a Severed Ear",
      "hook": "A captain's pickled ear helped start a war.",
      "category": "weird-wars",
      "series_id": "weird-wars",
      "series_name": "Weird Wars",
      "episode_number": 10,
      "fact_theory_note": "FACT/THEORY: War of Jenkins' Ear, 1739; the ear-in-Parliament story is partly legend.",
      "source_confidence": "medium",
      "scores": {
        "hook": 9,
        "mystery": 7,
        "shareability": 9,
        "visual": 6,
        "credibility": 7,
        "search": 7,
        "series": 7,
        "total": 99
      },
      "shorts_eligible": false
    },
    {
      "slug": "piri-reis-map",
      "title": "A 1513 Map That Seems to Show Too Much",
      "hook": "A 500-year-old map drawn with strange accuracy.",
      "category": "impossible-artifacts",
      "series_id": "impossible-artifacts",
      "series_name": "Impossible Artifacts",
      "episode_number": 7,
      "fact_theory_note": "FACT: Piri Reis map real, 1513; 'shows Antarctica' claims are THEORY/overstated.",
      "source_confidence": "medium",
      "scores": {
        "hook": 8,
        "mystery": 8,
        "shareability": 8,
        "visual": 8,
        "credibility": 6,
        "search": 7,
        "series": 8,
        "total": 99
      },
      "shorts_eligible": true
    },
    {
      "slug": "laki-1783",
      "title": "A Volcano in Iceland Helped Starve Europe",
      "hook": "An eruption poisoned skies and crops across a continent.",
      "category": "forgotten-disasters",
      "series_id": "forgotten-disasters",
      "series_name": "Forgotten Disasters",
      "episode_number": 13,
      "fact_theory_note": "FACT/THEORY: 1783 Laki eruption; downstream famine/death links partly modeled.",
      "source_confidence": "medium",
      "scores": {
        "hook": 8,
        "mystery": 8,
        "shareability": 8,
        "visual": 7,
        "credibility": 8,
        "search": 5,
        "series": 8,
        "total": 99
      },
      "shorts_eligible": true
    },
    {
      "slug": "la-perouse",
      "title": "A French Expedition Vanished and Took Decades to Find",
      "hook": "Two ships sailed the Pacific and simply stopped reporting.",
      "category": "lost-expeditions",
      "series_id": "lost-expeditions",
      "series_name": "Lost Expeditions",
      "episode_number": 8,
      "fact_theory_note": "FACT: La Perouse expedition lost ~1788; wrecks later found at Vanikoro.",
      "source_confidence": "high",
      "scores": {
        "hook": 8,
        "mystery": 8,
        "shareability": 8,
        "visual": 7,
        "credibility": 8,
        "search": 5,
        "series": 8,
        "total": 99
      },
      "shorts_eligible": true
    },
    {
      "slug": "darien-scheme",
      "title": "A Disaster That Bankrupted an Entire Nation",
      "hook": "Scotland gambled its fortune on a colony and lost everything.",
      "category": "lost-expeditions",
      "series_id": "lost-expeditions",
      "series_name": "Lost Expeditions",
      "episode_number": 13,
      "fact_theory_note": "FACT: Darien scheme, 1690s; contributed to the 1707 Union.",
      "source_confidence": "high",
      "scores": {
        "hook": 8,
        "mystery": 8,
        "shareability": 8,
        "visual": 6,
        "credibility": 9,
        "search": 5,
        "series": 8,
        "total": 99
      },
      "shorts_eligible": false
    },
    {
      "slug": "ambrose-bierce",
      "title": "A Famous Writer Rode Into a War and Vanished",
      "hook": "He wrote his own ending: 'to be a gringo in Mexico...'",
      "category": "disappearances",
      "series_id": "disappearances",
      "series_name": "Historical Disappearances",
      "episode_number": 9,
      "fact_theory_note": "FACT: Bierce disappeared ~1913-14 in Mexico; fate unknown.",
      "source_confidence": "high",
      "scores": {
        "hook": 8,
        "mystery": 8,
        "shareability": 8,
        "visual": 6,
        "credibility": 8,
        "search": 6,
        "series": 8,
        "total": 98
      },
      "shorts_eligible": false
    },
    {
      "slug": "bobby-dunbar",
      "title": "A 'Found' Missing Boy Wasn't Who Everyone Thought",
      "hook": "DNA a century later revealed the wrong child grew up in his place.",
      "category": "disappearances",
      "series_id": "disappearances",
      "series_name": "Historical Disappearances",
      "episode_number": 17,
      "fact_theory_note": "FACT: 1912 case; 2004 DNA showed misidentification.",
      "source_confidence": "high",
      "scores": {
        "hook": 8,
        "mystery": 9,
        "shareability": 8,
        "visual": 5,
        "credibility": 9,
        "search": 5,
        "series": 7,
        "total": 98
      },
      "shorts_eligible": false
    },
    {
      "slug": "patient-hm",
      "title": "A Man Who Couldn't Make New Memories for 50 Years",
      "hook": "Surgery erased his ability to remember anything new.",
      "category": "medical-history",
      "series_id": "medical-history",
      "series_name": "Strange Medical History",
      "episode_number": 8,
      "fact_theory_note": "FACT: Henry Molaison (H.M.); foundational memory neuroscience.",
      "source_confidence": "high",
      "scores": {
        "hook": 8,
        "mystery": 8,
        "shareability": 8,
        "visual": 5,
        "credibility": 9,
        "search": 6,
        "series": 8,
        "total": 98
      },
      "shorts_eligible": false
    },
    {
      "slug": "pantheon-dome",
      "title": "The Largest Concrete Dome Stood for 1,900 Years",
      "hook": "Unreinforced concrete that still holds the record.",
      "category": "ancient-engineering",
      "series_id": "ancient-engineering",
      "series_name": "Ancient Engineering",
      "episode_number": 8,
      "fact_theory_note": "FACT: Pantheon's dome is the largest unreinforced concrete dome.",
      "source_confidence": "high",
      "scores": {
        "hook": 7,
        "mystery": 6,
        "shareability": 7,
        "visual": 9,
        "credibility": 9,
        "search": 7,
        "series": 7,
        "total": 97
      },
      "shorts_eligible": true
    },
    {
      "slug": "william-buckland",
      "title": "A Scientist Who Tried to Eat Every Animal on Earth",
      "hook": "He claimed to have eaten a king's preserved heart.",
      "category": "made-up-humans",
      "series_id": "made-up-humans",
      "series_name": "Humans That Sound Made Up",
      "episode_number": 12,
      "fact_theory_note": "FACT/THEORY: Buckland's 'zoophagy' attested; the royal-heart anecdote is traditional.",
      "source_confidence": "medium",
      "scores": {
        "hook": 9,
        "mystery": 7,
        "shareability": 9,
        "visual": 6,
        "credibility": 7,
        "search": 5,
        "series": 7,
        "total": 97
      },
      "shorts_eligible": false
    },
    {
      "slug": "greely-expedition",
      "title": "An Arctic Mission Ended in Starvation and Whispered Horrors",
      "hook": "Of 25 men, 6 came home — and questions followed.",
      "category": "lost-expeditions",
      "series_id": "lost-expeditions",
      "series_name": "Lost Expeditions",
      "episode_number": 7,
      "fact_theory_note": "FACT/THEORY: Greely expedition 1881-84; cannibalism allegations contested.",
      "source_confidence": "medium",
      "scores": {
        "hook": 8,
        "mystery": 9,
        "shareability": 8,
        "visual": 6,
        "credibility": 7,
        "search": 5,
        "series": 8,
        "total": 97
      },
      "shorts_eligible": false
    },
    {
      "slug": "narvaez-expedition",
      "title": "A 600-Man Expedition Ended With 4 Survivors Walking Across a Continent",
      "hook": "Eight years lost in the Americas.",
      "category": "lost-expeditions",
      "series_id": "lost-expeditions",
      "series_name": "Lost Expeditions",
      "episode_number": 12,
      "fact_theory_note": "FACT: Narvaez expedition 1527; Cabeza de Vaca's account survives.",
      "source_confidence": "high",
      "scores": {
        "hook": 8,
        "mystery": 8,
        "shareability": 8,
        "visual": 6,
        "credibility": 8,
        "search": 5,
        "series": 8,
        "total": 97
      },
      "shorts_eligible": false
    },
    {
      "slug": "football-war",
      "title": "A Soccer Match Started a Real War",
      "hook": "Two nations went to war after a World Cup qualifier.",
      "category": "weird-wars",
      "series_id": "weird-wars",
      "series_name": "Weird Wars",
      "episode_number": 5,
      "fact_theory_note": "FACT: 1969 El Salvador-Honduras; football was a flashpoint, not sole cause (note tensions).",
      "source_confidence": "high",
      "scores": {
        "hook": 8,
        "mystery": 7,
        "shareability": 8,
        "visual": 6,
        "credibility": 8,
        "search": 7,
        "series": 7,
        "total": 96
      },
      "shorts_eligible": false
    },
    {
      "slug": "battle-karansebes",
      "title": "An Army Attacked Itself and Lost Thousands",
      "hook": "The Austrian army panicked and fought... itself.",
      "category": "weird-wars",
      "series_id": "weird-wars",
      "series_name": "Weird Wars",
      "episode_number": 14,
      "fact_theory_note": "THEORY: 1788 Battle of Karansebes; casualty figures and details are disputed/possibly exaggerated.",
      "source_confidence": "low",
      "scores": {
        "hook": 9,
        "mystery": 8,
        "shareability": 9,
        "visual": 6,
        "credibility": 5,
        "search": 6,
        "series": 7,
        "total": 96
      },
      "shorts_eligible": false
    },
    {
      "slug": "whisky-war",
      "title": "Two Nations Fought 50 Years by Swapping Bottles",
      "hook": "Canada and Denmark 'attacked' an island with liquor.",
      "category": "weird-wars",
      "series_id": "weird-wars",
      "series_name": "Weird Wars",
      "episode_number": 15,
      "fact_theory_note": "FACT: Whisky War over Hans Island; resolved 2022.",
      "source_confidence": "high",
      "scores": {
        "hook": 8,
        "mystery": 6,
        "shareability": 8,
        "visual": 6,
        "credibility": 9,
        "search": 7,
        "series": 7,
        "total": 96
      },
      "shorts_eligible": false
    },
    {
      "slug": "war-stray-dog",
      "title": "A Runaway Dog Started a War Between Nations",
      "hook": "A soldier chasing his dog sparked an invasion.",
      "category": "weird-wars",
      "series_id": "weird-wars",
      "series_name": "Weird Wars",
      "episode_number": 17,
      "fact_theory_note": "FACT/THEORY: 1925 War of the Stray Dog, Greece-Bulgaria; the dog anecdote is traditional.",
      "source_confidence": "medium",
      "scores": {
        "hook": 9,
        "mystery": 7,
        "shareability": 9,
        "visual": 5,
        "credibility": 7,
        "search": 6,
        "series": 7,
        "total": 96
      },
      "shorts_eligible": false
    },
    {
      "slug": "bennington-triangle",
      "title": "People Kept Vanishing on the Same Mountain",
      "hook": "Several disappeared on Glastenbury — some never found.",
      "category": "disappearances",
      "series_id": "disappearances",
      "series_name": "Historical Disappearances",
      "episode_number": 15,
      "fact_theory_note": "FACT: real 1940s Vermont disappearances; 'triangle' link is THEORY/folklore.",
      "source_confidence": "medium",
      "scores": {
        "hook": 8,
        "mystery": 8,
        "shareability": 8,
        "visual": 6,
        "credibility": 7,
        "search": 6,
        "series": 8,
        "total": 96
      },
      "shorts_eligible": false
    },
    {
      "slug": "benjamin-bathurst",
      "title": "A Diplomat Walked Around His Horses and Vanished",
      "hook": "He stepped behind a coach in 1809 and was gone.",
      "category": "disappearances",
      "series_id": "disappearances",
      "series_name": "Historical Disappearances",
      "episode_number": 16,
      "fact_theory_note": "FACT/THEORY: Bathurst disappeared 1809; details embellished over time.",
      "source_confidence": "low",
      "scores": {
        "hook": 9,
        "mystery": 8,
        "shareability": 9,
        "visual": 5,
        "credibility": 6,
        "search": 5,
        "series": 8,
        "total": 96
      },
      "shorts_eligible": false
    },
    {
      "slug": "maine-penny",
      "title": "A Viking Coin Found in Native American Ruins",
      "hook": "An 11th-century Norse coin, thousands of miles from home.",
      "category": "impossible-artifacts",
      "series_id": "impossible-artifacts",
      "series_name": "Impossible Artifacts",
      "episode_number": 12,
      "fact_theory_note": "FACT: Maine penny is a genuine Norse coin; how it arrived is THEORY (trade vs. hoax).",
      "source_confidence": "medium",
      "scores": {
        "hook": 8,
        "mystery": 9,
        "shareability": 8,
        "visual": 6,
        "credibility": 7,
        "search": 5,
        "series": 7,
        "total": 96
      },
      "shorts_eligible": false
    },
    {
      "slug": "collyer-brothers",
      "title": "Two Brothers Buried Alive in Their Own Hoard",
      "hook": "Booby-trapped tunnels of junk filled their mansion.",
      "category": "made-up-humans",
      "series_id": "made-up-humans",
      "series_name": "Humans That Sound Made Up",
      "episode_number": 15,
      "fact_theory_note": "FACT: Collyer brothers, 1947; ~140 tons removed.",
      "source_confidence": "high",
      "scores": {
        "hook": 8,
        "mystery": 8,
        "shareability": 8,
        "visual": 6,
        "credibility": 8,
        "search": 5,
        "series": 7,
        "total": 96
      },
      "shorts_eligible": false
    },
    {
      "slug": "pharos-alexandria",
      "title": "A 100m Lighthouse Stood for 1,600 Years",
      "hook": "One of the Seven Wonders guided ships with fire and mirrors.",
      "category": "ancient-engineering",
      "series_id": "ancient-engineering",
      "series_name": "Ancient Engineering",
      "episode_number": 11,
      "fact_theory_note": "FACT: Lighthouse of Alexandria real; exact height/mirror details THEORY.",
      "source_confidence": "high",
      "scores": {
        "hook": 7,
        "mystery": 7,
        "shareability": 7,
        "visual": 8,
        "credibility": 8,
        "search": 7,
        "series": 7,
        "total": 95
      },
      "shorts_eligible": true
    },
    {
      "slug": "cocoanut-grove-fire",
      "title": "A Nightclub Fire That Changed Safety Laws Forever",
      "hook": "492 died in minutes behind locked exits.",
      "category": "forgotten-disasters",
      "series_id": "forgotten-disasters",
      "series_name": "Forgotten Disasters",
      "episode_number": 14,
      "fact_theory_note": "FACT: 1942 Cocoanut Grove fire; led to safety reforms.",
      "source_confidence": "high",
      "scores": {
        "hook": 8,
        "mystery": 6,
        "shareability": 8,
        "visual": 6,
        "credibility": 9,
        "search": 6,
        "series": 7,
        "total": 95
      },
      "shorts_eligible": false
    },
    {
      "slug": "aberfan-disaster",
      "title": "A Mountain of Coal Waste Buried a School",
      "hook": "144 died, most of them children, in seconds.",
      "category": "forgotten-disasters",
      "series_id": "forgotten-disasters",
      "series_name": "Forgotten Disasters",
      "episode_number": 15,
      "fact_theory_note": "FACT: 1966 Aberfan disaster; colliery spoil tip collapse.",
      "source_confidence": "high",
      "scores": {
        "hook": 8,
        "mystery": 6,
        "shareability": 8,
        "visual": 6,
        "credibility": 9,
        "search": 6,
        "series": 7,
        "total": 95
      },
      "shorts_eligible": false
    },
    {
      "slug": "saqqara-bird",
      "title": "An Ancient Egyptian Object Shaped Like a Plane",
      "hook": "Did Egyptians understand flight?",
      "category": "impossible-artifacts",
      "series_id": "impossible-artifacts",
      "series_name": "Impossible Artifacts",
      "episode_number": 13,
      "fact_theory_note": "FACT: artifact exists; 'glider' interpretation is THEORY, rejected by most experts.",
      "source_confidence": "low",
      "scores": {
        "hook": 8,
        "mystery": 8,
        "shareability": 8,
        "visual": 7,
        "credibility": 5,
        "search": 7,
        "series": 7,
        "total": 94
      },
      "shorts_eligible": false
    },
    {
      "slug": "qanat-systems",
      "title": "Ancient Tunnels That Carried Water Across Deserts",
      "hook": "Persians moved water 50 miles underground by hand.",
      "category": "ancient-engineering",
      "series_id": "ancient-engineering",
      "series_name": "Ancient Engineering",
      "episode_number": 4,
      "fact_theory_note": "FACT: qanat/karez systems, millennia old, still used.",
      "source_confidence": "high",
      "scores": {
        "hook": 7,
        "mystery": 6,
        "shareability": 7,
        "visual": 8,
        "credibility": 9,
        "search": 6,
        "series": 7,
        "total": 94
      },
      "shorts_eligible": true
    },
    {
      "slug": "peter-wild-boy",
      "title": "A Feral Boy Was Raised in a Royal Court",
      "hook": "A child found in the woods became a king's pet curiosity.",
      "category": "made-up-humans",
      "series_id": "made-up-humans",
      "series_name": "Humans That Sound Made Up",
      "episode_number": 11,
      "fact_theory_note": "FACT/THEORY: Peter the Wild Boy real; modern view: likely Pitt-Hopkins syndrome.",
      "source_confidence": "medium",
      "scores": {
        "hook": 8,
        "mystery": 8,
        "shareability": 8,
        "visual": 6,
        "credibility": 7,
        "search": 5,
        "series": 7,
        "total": 94
      },
      "shorts_eligible": false
    },
    {
      "slug": "pastry-war",
      "title": "France Invaded Mexico Over a Pastry Bill",
      "hook": "A baker's unpaid debt led to a French invasion.",
      "category": "weird-wars",
      "series_id": "weird-wars",
      "series_name": "Weird Wars",
      "episode_number": 12,
      "fact_theory_note": "FACT/THEORY: 'Pastry War' 1838; the pastry claim was one pretext among debts.",
      "source_confidence": "medium",
      "scores": {
        "hook": 8,
        "mystery": 7,
        "shareability": 8,
        "visual": 6,
        "credibility": 7,
        "search": 6,
        "series": 7,
        "total": 93
      },
      "shorts_eligible": false
    },
    {
      "slug": "golden-stool-war",
      "title": "A War Fought Over a Sacred Golden Throne",
      "hook": "A British demand to sit on a stool sparked rebellion.",
      "category": "weird-wars",
      "series_id": "weird-wars",
      "series_name": "Weird Wars",
      "episode_number": 18,
      "fact_theory_note": "FACT: War of the Golden Stool, 1900, Ashanti vs Britain.",
      "source_confidence": "high",
      "scores": {
        "hook": 7,
        "mystery": 7,
        "shareability": 7,
        "visual": 7,
        "credibility": 9,
        "search": 6,
        "series": 6,
        "total": 93
      },
      "shorts_eligible": true
    },
    {
      "slug": "cod-wars",
      "title": "Britain and Iceland Fought Wars Over Fish",
      "hook": "NATO allies rammed each other's ships over cod.",
      "category": "weird-wars",
      "series_id": "weird-wars",
      "series_name": "Weird Wars",
      "episode_number": 9,
      "fact_theory_note": "FACT: Cod Wars, mid-20th c.; ship ramming and net-cutting documented.",
      "source_confidence": "high",
      "scores": {
        "hook": 7,
        "mystery": 6,
        "shareability": 7,
        "visual": 7,
        "credibility": 9,
        "search": 6,
        "series": 7,
        "total": 92
      },
      "shorts_eligible": true
    },
    {
      "slug": "paraguay-war",
      "title": "A War That Killed Most of a Country's Men",
      "hook": "Paraguay lost up to 70% of its adult men in one war.",
      "category": "weird-wars",
      "series_id": "weird-wars",
      "series_name": "Weird Wars",
      "episode_number": 8,
      "fact_theory_note": "FACT/THEORY: War of the Triple Alliance 1864-70; mortality estimates debated.",
      "source_confidence": "medium",
      "scores": {
        "hook": 7,
        "mystery": 8,
        "shareability": 7,
        "visual": 6,
        "credibility": 8,
        "search": 5,
        "series": 6,
        "total": 90
      },
      "shorts_eligible": false
    },
    {
      "slug": "lijar-100-years",
      "title": "A Spanish Town Was 'At War' With France for 100 Years",
      "hook": "Lijar declared war on France and forgot to stop.",
      "category": "weird-wars",
      "series_id": "weird-wars",
      "series_name": "Weird Wars",
      "episode_number": 13,
      "fact_theory_note": "FACT: Lijar 'declared war' 1883, symbolically ended 1981.",
      "source_confidence": "medium",
      "scores": {
        "hook": 8,
        "mystery": 7,
        "shareability": 8,
        "visual": 5,
        "credibility": 7,
        "search": 6,
        "series": 6,
        "total": 90
      },
      "shorts_eligible": false
    },
    {
      "slug": "theodosia-burr",
      "title": "A Vice President's Daughter Vanished at Sea",
      "hook": "She boarded a ship in 1813 and was never seen again.",
      "category": "disappearances",
      "series_id": "disappearances",
      "series_name": "Historical Disappearances",
      "episode_number": 13,
      "fact_theory_note": "FACT: Theodosia Burr Alston lost at sea 1813; fate THEORY.",
      "source_confidence": "medium",
      "scores": {
        "hook": 7,
        "mystery": 8,
        "shareability": 7,
        "visual": 6,
        "credibility": 7,
        "search": 5,
        "series": 8,
        "total": 90
      },
      "shorts_eligible": false
    },
    {
      "slug": "toledo-war",
      "title": "Ohio and Michigan Went to War Over Toledo",
      "hook": "Two US states nearly fought over a strip of mud.",
      "category": "weird-wars",
      "series_id": "weird-wars",
      "series_name": "Weird Wars",
      "episode_number": 11,
      "fact_theory_note": "FACT: Toledo War 1835-36, essentially bloodless.",
      "source_confidence": "high",
      "scores": {
        "hook": 7,
        "mystery": 6,
        "shareability": 7,
        "visual": 6,
        "credibility": 8,
        "search": 6,
        "series": 7,
        "total": 88
      },
      "shorts_eligible": false
    },
    {
      "slug": "utah-war",
      "title": "The War Almost Nobody Died In",
      "hook": "An entire US army marched on Utah — and barely fought.",
      "category": "weird-wars",
      "series_id": "weird-wars",
      "series_name": "Weird Wars",
      "episode_number": 19,
      "fact_theory_note": "FACT: Utah War 1857-58, largely bloodless (but note Mountain Meadows separately).",
      "source_confidence": "medium",
      "scores": {
        "hook": 6,
        "mystery": 6,
        "shareability": 6,
        "visual": 6,
        "credibility": 8,
        "search": 5,
        "series": 6,
        "total": 81
      },
      "shorts_eligible": false
    },
    {
      "slug": "daniel-lambert",
      "title": "A Man So Beloved People Paid Just to Meet Him",
      "hook": "Britain's gentle giant became a folk hero.",
      "category": "made-up-humans",
      "series_id": "made-up-humans",
      "series_name": "Humans That Sound Made Up",
      "episode_number": 10,
      "fact_theory_note": "FACT: Daniel Lambert, early 1800s; treat with dignity.",
      "source_confidence": "medium",
      "scores": {
        "hook": 6,
        "mystery": 6,
        "shareability": 6,
        "visual": 6,
        "credibility": 8,
        "search": 4,
        "series": 7,
        "total": 81
      },
      "shorts_eligible": false
    },
    {
      "slug": "aroostook-war",
      "title": "The Bloodless War Over a Forest",
      "hook": "Two armies massed over trees — nobody died in battle.",
      "category": "weird-wars",
      "series_id": "weird-wars",
      "series_name": "Weird Wars",
      "episode_number": 16,
      "fact_theory_note": "FACT: Aroostook War 1838-39, no combat deaths.",
      "source_confidence": "medium",
      "scores": {
        "hook": 6,
        "mystery": 6,
        "shareability": 6,
        "visual": 5,
        "credibility": 8,
        "search": 5,
        "series": 6,
        "total": 79
      },
      "shorts_eligible": false
    }
  ]
}
