{
  "version": 8,
  "slug": "tropical-storm-arthur-texas-landfall",
  "title": "Tropical Storm Arthur Made Landfall in Texas. Hurricane Season Starts Early.",
  "script": "First storm of the season — landed already? Tropical Storm Arthur made landfall on the Texas coast Tuesday, becoming the first named storm of the 2026 Atlantic hurricane season — and it wasted no time. Arthur formed in the Gulf, strengthened fast, and hit the Bolivar Peninsula hard. At least 2 people are dead. More than 180 flooding reports across Texas, Louisiana, Mississippi, and Alabama since Sunday. Over 17 million people are under flood watches from eastern Texas to Georgia. The National Hurricane Center warned of life-threatening flash floods through Friday. Storm surge reached 2 to 4 feet near Morgan City, Louisiana. Meteorologists say this is an unusually early and active start to hurricane season. So: how many named storms are we looking at before this season is over?",
  "shots": [
    {
      "phrase": "First storm of the season — landed already?",
      "image_url": "https://commons.wikimedia.org/wiki/Special:FilePath/Arthur_2026_path.png",
      "query": "hurricane warning season tropical storm preparation",
      "mascot_pose": "shock"
    },
    {
      "phrase": "Tropical Storm Arthur made landfall on the Texas coast Tuesday",
      "image_url": "https://commons.wikimedia.org/wiki/Special:FilePath/Arthur_2026_path.png",
      "query": "Texas coast storm landfall weather surge",
      "mascot_pose": "point"
    },
    {
      "phrase": "the first named storm of the 2026 Atlantic hurricane season",
      "image_url": "https://commons.wikimedia.org/wiki/Special:FilePath/Arthur_2026_path.png",
      "query": "Atlantic hurricane season track map 2026 forecast",
      "mascot_pose": "idle"
    },
    {
      "phrase": "Arthur formed in the Gulf, strengthened fast, and hit the Bolivar Peninsula hard.",
      "image_url": "https://commons.wikimedia.org/wiki/Special:FilePath/Arthur_2026_path.png",
      "query": "Gulf of Mexico tropical storm satellite view",
      "mascot_pose": "idle"
    },
    {
      "phrase": "At least 2 people are dead.",
      "image_url": "https://commons.wikimedia.org/wiki/Special:FilePath/Arthur_2026_path.png",
      "query": "storm flood rescue emergency water rising",
      "mascot_pose": "shock"
    },
    {
      "phrase": "More than 180 flooding reports across Texas, Louisiana, Mississippi, and Alabama since Sunday.",
      "image_url": "https://commons.wikimedia.org/wiki/Special:FilePath/Arthur_2026_path.png",
      "query": "Louisiana Texas street flooding submerged cars",
      "mascot_pose": "idle"
    },
    {
      "phrase": "Over 17 million people are under flood watches from eastern Texas to Georgia.",
      "image_url": "https://commons.wikimedia.org/wiki/Special:FilePath/Arthur_2026_path.png",
      "query": "flood watch map southeast United States emergency alert",
      "mascot_pose": "idle"
    },
    {
      "phrase": "life-threatening flash floods through Friday.",
      "image_url": "https://commons.wikimedia.org/wiki/Special:FilePath/Arthur_2026_path.png",
      "query": "flash flood rushing water street neighborhood",
      "mascot_pose": "idle"
    },
    {
      "phrase": "Storm surge reached 2 to 4 feet near Morgan City, Louisiana.",
      "image_url": "https://commons.wikimedia.org/wiki/Special:FilePath/Arthur_2026_path.png",
      "query": "storm surge coastal flooding Louisiana shoreline",
      "mascot_pose": "idle"
    },
    {
      "phrase": "Meteorologists say this is an unusually early and active start to hurricane season.",
      "image_url": "https://commons.wikimedia.org/wiki/Special:FilePath/Arthur_2026_path.png",
      "query": "hurricane forecast cone track meteorologist map",
      "mascot_pose": "idle"
    },
    {
      "phrase": "how many named storms are we looking at before this season is over?",
      "image_url": "https://commons.wikimedia.org/wiki/Special:FilePath/Arthur_2026_path.png",
      "query": "hurricane season 2026 named storms Atlantic forecast",
      "mascot_pose": "dismiss"
    }
  ],
  "punches": [
    {
      "phrase": "First storm of the season — landed already?",
      "text": "SEASON 1 IS HERE",
      "color": "#ff3030"
    },
    {
      "phrase": "At least 2 people are dead.",
      "text": "2 DEAD",
      "color": "#ff3030"
    },
    {
      "phrase": "More than 180 flooding reports",
      "text": "180+ FLOOD REPORTS",
      "color": "#ff3030"
    },
    {
      "phrase": "Over 17 million people are under flood watches",
      "text": "17 MILLION UNDER WATCH",
      "color": "#ff3030"
    },
    {
      "phrase": "life-threatening flash floods through Friday.",
      "text": "LIFE-THREATENING FLOODS",
      "color": "#ff3030"
    },
    {
      "phrase": "Storm surge reached 2 to 4 feet near Morgan City, Louisiana.",
      "text": "4-FOOT SURGE",
      "color": "#ffaa30"
    }
  ],
  "hashtags": [
    "tropicalstormarthur",
    "arthur2026",
    "texasflooding",
    "hurricaneseason2026",
    "gulfcoaststorm",
    "bolivarpeninsula",
    "morgancity",
    "texasstorm",
    "floodwatch",
    "flashfloods",
    "hurricaneseason",
    "stormseason",
    "texasweather",
    "gulfstorm",
    "nationalhurricanecenter"
  ],
  "music_vibe": "dark",
  "bottom_theme": "auto"
}
